Metadata-Version: 2.1
Name: odoo13-addon-stock-location-address-purchase
Version: 13.0.1.0.1
Summary: Uses the location address on purchases
Home-page: https://github.com/purchase-workflow
Author: Creu Blanca, Odoo Community Association (OCA)
Author-email: support@odoo-community.org
License: LGPL-3
Platform: UNKNOWN
Classifier: Programming Language :: Python
Classifier: Framework :: Odoo
Classifier: License :: OSI Approved :: GNU Lesser General Public License v3 (LGPLv3)
Requires-Python: >=3.5
Requires-Dist: odoo13-addon-stock-location-address
Requires-Dist: odoo (<13.1dev,>=13.0a)
